hymir/__init__.py
hymir/config.py
hymir/errors.py
hymir/executor.py
hymir/executors/__init__.py
hymir/executors/celery.py
hymir/job.py
hymir/types.py
hymir/utils.py
hymir/visualize.py
hymir/workflow.py
hymir-0.1.9.dist-info/LICENSE
hymir-0.1.9.dist-info/METADATA
hymir-0.1.9.dist-info/WHEEL
hymir-0.1.9.dist-info/RECORD
